discord_argparse/__init__.py
discord_argparse/argparse.py
discord_argparse/errors.py
discord_argparse-1.0.1.dist-info/LICENSE
discord_argparse-1.0.1.dist-info/METADATA
discord_argparse-1.0.1.dist-info/WHEEL
discord_argparse-1.0.1.dist-info/top_level.txt
discord_argparse-1.0.1.dist-info/RECORD
