Metadata-Version: 2.1
Name: discord-argparse
Version: 1.0.1
Summary: Arbitrarily ordered arguments for commands in discord.py
Home-page: https://github.com/lukeciel/discord-argparse
Author: lukeciel
License: MIT
Platform: UNKNOWN
Requires-Dist: discord.py (>=1.0.0)
